framework/__init__.py
framework/models/__init__.py
framework/models/base_keras_model.py
framework/models/base_keras_sklearn_model.py
framework/models/base_model.py
framework/models/base_xgboost_model.py
framework/tools/__init__.py
framework/tools/calc_metrics.py
framework/tools/log.py
framework/tools/mmr.py
framework/tools/rank_metrics.py
plugins/__init__.py
plugins/ctr/__init__.py
plugins/ctr/wide_and_deep_official/__init__.py
plugins/ctr/wide_and_deep_official/tt_dataset.py
plugins/ctr/wide_and_deep_official/tt_main.py
plugins/ctr/wide_and_deep_official/wide_deep_run_loop.py
plugins/graph/__init__.py
plugins/itemcf/__init__.py
plugins/nlp/__init__.py
plugins/rl/__init__.py
plugins/usercf/__init__.py
plugins/video/__init__.py
scripts/__init__.py
scripts/common_import.py
scripts/keras_demo.py
scripts/keras_multi_demo.py
scripts/pure_keras_demo.py
scripts/xgboost_demo.py
scripts/xgboost_plot.py
grace_t-0.0.3.1.dist-info/METADATA
grace_t-0.0.3.1.dist-info/WHEEL
grace_t-0.0.3.1.dist-info/top_level.txt
grace_t-0.0.3.1.dist-info/RECORD
